energysandbox/__init__.py
energysandbox/joyn.py
energysandbox-0.0.5.dist-info/LICENSE.txt
energysandbox-0.0.5.dist-info/METADATA
energysandbox-0.0.5.dist-info/WHEEL
energysandbox-0.0.5.dist-info/top_level.txt
energysandbox-0.0.5.dist-info/RECORD
